ipalab_config/__init__.py
ipalab_config/__main__.py
ipalab_config/compose.py
ipalab_config/inventory.py
ipalab_config/logger.py
ipalab_config/utils.py
ipalab_config/data/containerfiles/centos
ipalab_config/data/containerfiles/external-nodes
ipalab_config/data/containerfiles/fedora
ipalab_config/data/containerfiles/ubuntu
ipalab_config/data/keycloak/Containerfile
ipalab_config/data/keycloak/keycloak_add_oidc_client.sh
ipalab_config/data/keycloak/keycloak_add_user.sh
ipalab_config/data/keycloak/keycloak_functions.sh
ipalab_config/data/keycloak/trust_keycloak.sh
ipalab_config/data/playbooks/deploy_addc.yml
ipalab_config/data/scripts/open-firefox.sh
ipalab_config/data/unbound/Containerfile
ipalab_config/data/unbound/unbound.conf
ipalab_config/external_role/addc.py
ipalab_config/external_role/dns.py
ipalab_config/external_role/keycloak.py
ipalab_config-0.15.2.dist-info/licenses/COPYING
ipalab_config-0.15.2.dist-info/METADATA
ipalab_config-0.15.2.dist-info/WHEEL
ipalab_config-0.15.2.dist-info/entry_points.txt
ipalab_config-0.15.2.dist-info/top_level.txt
ipalab_config-0.15.2.dist-info/RECORD
