Metadata-Version: 2.4
Name: ipalab-config
Version: 0.15.2
Summary: Generates compose and inventory files to create a container based FreeIPA cluster.
Author-email: Rafael Guterres Jeffman <rjeffman@redhat.com>
License: 0BSD
Keywords: freeipa,ansible
Classifier: Development Status :: 4 - Beta
Classifier: Intended Audience :: Developers
Classifier: Intended Audience :: System Administrators
Classifier: License :: OSI Approved :: Zero-Clause BSD (0BSD)
Classifier: Framework :: Ansible
Requires-Python: >=3.6
License-File: COPYING
Requires-Dist: ruamel.yaml
Provides-Extra: dev
Requires-Dist: black; extra == "dev"
Requires-Dist: pre-commit; extra == "dev"
Requires-Dist: pylint; extra == "dev"
Requires-Dist: yamllint; extra == "dev"
Requires-Dist: behave>=1.2.7dev6; extra == "dev"
Provides-Extra: opt
Requires-Dist: jinja2; extra == "opt"
Provides-Extra: release
Requires-Dist: build; extra == "release"
Dynamic: license-file
